stardots_sdk/__init__.py
stardots_sdk/constants.py
stardots_sdk/helper.py
stardots_sdk/stardots.py
stardots_sdk/types.py
stardots_sdk_python-1.0.0.dist-info/LICENSE
stardots_sdk_python-1.0.0.dist-info/METADATA
stardots_sdk_python-1.0.0.dist-info/WHEEL
stardots_sdk_python-1.0.0.dist-info/top_level.txt
stardots_sdk_python-1.0.0.dist-info/RECORD
