Metadata-Version: 2.1
Name: stardots-sdk-python
Version: 1.0.0
Summary: StarDots SDK for Python 3
Home-page: https://stardots.io
Author: StarDots Team
Author-email: StarDots Team <support@stardots.io>
License: MIT
Requires-Python: >=3.7
License-File: LICENSE
Requires-Dist: requests>=2.25.0
Requires-Dist: pydantic>=1.10.0
